django_queryset_feeler/__init__.py
django_queryset_feeler/thing.py
django_queryset_feeler-0.0.6.dist-info/LICENSE
django_queryset_feeler-0.0.6.dist-info/METADATA
django_queryset_feeler-0.0.6.dist-info/WHEEL
django_queryset_feeler-0.0.6.dist-info/top_level.txt
django_queryset_feeler-0.0.6.dist-info/RECORD
