Metadata-Version: 2.1
Name: django-queryset-feeler
Version: 0.0.6
Summary: tools to help understand how django querysets are executed
Author-email: Lukas Schillinger <lukas@schillingertools.com>
License: MIT License
Project-URL: homepage, https://github.com/lukas-schillinger/django-queryset-feeler
Keywords: django,query,queryset
Classifier: Programming Language :: Python :: 3
Classifier: Operating System :: OS Independent
Classifier: Framework :: Django
Requires-Python: >=3.7
License-File: LICENSE
Requires-Dist: sqlparse >=0.4.2
Requires-Dist: django >=3.2
Requires-Dist: sql-metadata >=2.6.0
Requires-Dist: Pygments >=2.12.0
Requires-Dist: ipython >=8.4.0
Provides-Extra: test
Requires-Dist: djangorestframework >=3.13.1 ; extra == 'test'
